dd/__init__.py
dd/camera.py
dd/dd_ai_onnx.py
dd/dd_api_groovy.py
dd/dd_java.py
dd/ph.py
dd/recorder.py
dd/robot.py
dd_ph-0.1.dist-info/METADATA
dd_ph-0.1.dist-info/WHEEL
dd_ph-0.1.dist-info/top_level.txt
dd_ph-0.1.dist-info/RECORD
